JSON_minify-0.3.0.dist-info/DESCRIPTION.rst
JSON_minify-0.3.0.dist-info/METADATA
JSON_minify-0.3.0.dist-info/RECORD
JSON_minify-0.3.0.dist-info/WHEEL
JSON_minify-0.3.0.dist-info/metadata.json
JSON_minify-0.3.0.dist-info/top_level.txt
json_minify/__init__.py
json_minify/test_json_minify.py
