Metadata-Version: 1.1
Name: JSON_minify
Version: 0.3.0
Summary: A simple script to minify valid JSON, containing C/C++ style comments
Home-page: https://github.com/getify/JSON.minify/tree/python
Author: Pradyun S. Gedam
Author-email: pradyunsg@gmail.com
License: MIT
Platform: UNKNOWN
Classifier: Programming Language :: Python :: 2
Classifier: Programming Language :: Python :: 3
Classifier: Intended Audience :: Developers
Classifier: License :: OSI Approved :: MIT License
Classifier: Topic :: Utilities
